doitoml/__init__.py
doitoml/_version.py
doitoml/config.py
doitoml/constants.py
doitoml/doitoml.py
doitoml/dsl.py
doitoml/entry_points.py
doitoml/errors.py
doitoml/loaders.py
doitoml/py.typed
doitoml/types.py
doitoml/actors/__init__.py
doitoml/actors/_actor.py
doitoml/actors/py.py
doitoml/schema/__init__.py
doitoml/schema/_v0.schema.json
doitoml/schema/_v0_schema.py
doitoml/schema/v0.schema.toml
doitoml/schema/validator.py
doitoml/skippers/__init__.py
doitoml/skippers/_skipper.py
doitoml/skippers/bools.py
doitoml/skippers/path.py
doitoml/skippers/py.py
doitoml/sources/__init__.py
doitoml/sources/_config.py
doitoml/sources/_source.py
doitoml/sources/json/__init__.py
doitoml/sources/json/_json.py
doitoml/sources/json/package.py
doitoml/sources/toml/__init__.py
doitoml/sources/toml/_toml.py
doitoml/sources/toml/pyproject.py
doitoml/sources/yaml/__init__.py
doitoml/sources/yaml/_yaml.py
doitoml/templaters/__init__.py
doitoml/templaters/_templater.py
doitoml/templaters/jinja2.py
doitoml/templaters/jsone.py
doitoml/updaters/__init__.py
doitoml/updaters/_updater.py
doitoml/updaters/doit_tools.py
doitoml/updaters/py.py
doitoml/utils/__init__.py
doitoml/utils/json.py
doitoml/utils/log.py
doitoml/utils/path.py
doitoml/utils/py.py
doitoml-0.2.0.dist-info/entry_points.txt
doitoml-0.2.0.dist-info/LICENSE.txt
doitoml-0.2.0.dist-info/WHEEL
doitoml-0.2.0.dist-info/METADATA
doitoml-0.2.0.dist-info/RECORD
