Metadata-Version: 2.1
Name: doitoml
Version: 0.2.0
Summary: Load declarative tasks for doit from TOML, JSON, YAML, and other files.
Author-email: doitoml contributors <deathbeds@googlegroups.com>
Requires-Python: >=3.8
Classifier: License :: OSI Approved :: BSD License
Classifier: Programming Language :: Python :: 3 :: Only
Classifier: Programming Language :: Python :: 3
Requires-Dist: doit >=0.36.0
Requires-Dist: typing_extensions
Requires-Dist: tomli ; python_version<"3.11"
Requires-Dist: doitoml[json-e] ; extra == "all"
Requires-Dist: doitoml[jinja2] ; extra == "all"
Requires-Dist: doitoml[jsonschema] ; extra == "all"
Requires-Dist: doitoml[pyyaml] ; extra == "all"
Requires-Dist: jinja2 >=3 ; extra == "jinja2"
Requires-Dist: json-e >=4 ; extra == "json-e"
Requires-Dist: jsonschema >=4 ; extra == "jsonschema"
Requires-Dist: build ; extra == "test"
Requires-Dist: pytest-console-scripts ; extra == "test"
Requires-Dist: pytest-cov ; extra == "test"
Requires-Dist: pytest-html-report ; extra == "test"
Requires-Dist: pytest-json-report ; extra == "test"
Requires-Dist: pytest-xdist ; extra == "test"
Requires-Dist: tomli-w ; extra == "test"
Requires-Dist: pyyaml >=5 ; extra == "yaml"
Project-URL: Bug Tracker, https://github.com/deathbeds/doitoml/issues
Project-URL: Changelog, https://github.com/deathbeds/doitoml/blob/main/CHANGELOG.md
Project-URL: Documentation, https://doitoml.rtfd.io
Project-URL: PyPI, https://pypi.org/project/doitoml
Project-URL: Source, https://github.com/deathbeds/doitoml/tree/main
Provides-Extra: all
Provides-Extra: jinja2
Provides-Extra: json-e
Provides-Extra: jsonschema
Provides-Extra: test
Provides-Extra: yaml
